Metadata-Version: 1.1
Name: YTScraper
Version: 0.0.6
Summary: A command-line tool for downloading .torrent files from YTS.
Home-page: UNKNOWN
Author: Finbarrs Oketunji
Author-email: oketunjifinbarrs@gmail.com
License: MIT
Keywords: yts yify scraper media download downloader torrent
Platform: UNKNOWN
Classifier: Intended Audience :: Developers
Classifier: License :: DFSG approved
Classifier: License :: OSI Approved :: BSD License
Classifier: Operating System :: OS Independent
Classifier: Programming Language :: Python :: 2
Classifier: Programming Language :: Python :: 2.6
Classifier: Programming Language :: Python :: 2.7
Classifier: Programming Language :: Python :: 3
Classifier: Programming Language :: Python :: 3.4
Classifier: Programming Language :: Python :: 3.5
Classifier: Programming Language :: Python :: 3.6
Classifier: Topic :: Software Development :: Libraries :: Python Modules
